trackimo/__init__.py
trackimo/exceptions.py
trackimo/skeleton.py
trackimo/API/__init__.py
trackimo/API/main.py
trackimo/adddress/__init__.py
trackimo/adddress/geocode.py
trackimo/protocol/__init__.py
trackimo/protocol/account.py
trackimo/protocol/device.py
trackimo/protocol/protocol.py
trackimo/protocol/user.py
trackimo-0.1.30.dist-info/AUTHORS.rst
trackimo-0.1.30.dist-info/LICENSE.txt
trackimo-0.1.30.dist-info/METADATA
trackimo-0.1.30.dist-info/WHEEL
trackimo-0.1.30.dist-info/top_level.txt
trackimo-0.1.30.dist-info/RECORD
