Metadata-Version: 2.1
Name: trackimo
Version: 0.1.30
Summary: Get data from your Trackimo devices
Home-page: https://github.com/troykelly/python-trackimo
Author: Troy Kelly
Author-email: troy@troykelly.com
License: mit
Project-URL: Documentation, https://github.com/troykelly/python-trackimo/wiki
Platform: any
Classifier: Development Status :: 4 - Beta
Classifier: Programming Language :: Python
Requires-Dist: backoff
Requires-Dist: requests
Provides-Extra: testing
Requires-Dist: pytest ; extra == 'testing'
Requires-Dist: pytest-cov ; extra == 'testing'
